aiger_analysis/__init__.py
aiger_analysis/abc.py
aiger_analysis/analysis.py
aiger_analysis/bdd.py
aiger_analysis/cadet.py
aiger_analysis/common.py
aiger_analysis/count.py
aiger_analysis/safety_game.py
aiger_analysis/test_abc.py
aiger_analysis/test_analysis.py
aiger_analysis/test_bdd.py
aiger_analysis/test_cadet.py
aiger_analysis/test_count.py
aiger_analysis/test_safety_game.py
py_aiger_analysis-0.0.1.dist-info/METADATA
py_aiger_analysis-0.0.1.dist-info/RECORD
py_aiger_analysis-0.0.1.dist-info/WHEEL
py_aiger_analysis-0.0.1.dist-info/top_level.txt
